{
  "name": "ip.sb",
  "url": "https://api.ip.sb/geoip/8.8.8.8",
  "status": "success",
  "elapsed_ms": 20.92,
  "remark": "",
  "supports_ip": true,
  "result": {
    "organization": "Google",
    "isp": "Google",
    "asn_organization": "Google LLC",
    "asn": 15169,
    "offset": -21600,
    "latitude": 37.751,
    "ip": "8.8.8.8",
    "continent_code": "NA",
    "timezone": "America/Chicago",
    "country": "United States",
    "longitude": -97.822,
    "country_code": "US"
  },
  "error": null,
  "test_ip": "8.8.8.8"
}